{
  "page": 498,
  "image": "/books/page 498.png",
  "imageApiPath": "/api/books/page%20498.png",
  "layout": "quad",
  "stats": {
    "regionCount": 4,
    "wordCount": 71,
    "imageWidth": 1188,
    "imageHeight": 1875
  },
  "panels": [
    {
      "id": "top-right",
      "label": "Top Right",
      "x": 0.5,
      "y": 0,
      "w": 0.5,
      "h": 0.5,
      "regionIds": [
        "r1"
      ]
    },
    {
      "id": "bottom-left",
      "label": "Bottom Left",
      "x": 0,
      "y": 0.5,
      "w": 0.5,
      "h": 0.5,
      "regionIds": [
        "r3"
      ]
    },
    {
      "id": "bottom-right",
      "label": "Bottom Right",
      "x": 0.5,
      "y": 0.5,
      "w": 0.5,
      "h": 0.5,
      "regionIds": [
        "r2",
        "r4"
      ]
    }
  ],
  "regions": [
    {
      "text": "Cameras and eyes both form upside-down pictures. (Diagrams: Camera and eye showing inverted images of a person).",
      "x": 0.1,
      "y": 0.05,
      "w": 0.85,
      "h": 0.38,
      "id": "r1",
      "order": 0,
      "words": [
        "Cameras",
        "and",
        "eyes",
        "both",
        "form",
        "upside-down",
        "pictures.",
        "(Diagrams:",
        "Camera",
        "and",
        "eye",
        "showing",
        "inverted",
        "images",
        "of",
        "a",
        "person)."
      ]
    },
    {
      "text": "Light reaching the eye is physical. But in the retina, chemical changes happen, similar to how film records photos.",
      "x": 0.1,
      "y": 0.52,
      "w": 0.85,
      "h": 0.22,
      "id": "r2",
      "order": 1,
      "words": [
        "Light",
        "reaching",
        "the",
        "eye",
        "is",
        "physical.",
        "But",
        "in",
        "the",
        "retina,",
        "chemical",
        "changes",
        "happen,",
        "similar",
        "to",
        "how",
        "film",
        "records",
        "photos."
      ]
    },
    {
      "text": "(Illustration: A roll of film). These chemical changes cause even more complex changes in the retina's living cells.",
      "x": 0.1,
      "y": 0.75,
      "w": 0.55,
      "h": 0.22,
      "id": "r3",
      "order": 2,
      "words": [
        "(Illustration:",
        "A",
        "roll",
        "of",
        "film).",
        "These",
        "chemical",
        "changes",
        "cause",
        "even",
        "more",
        "complex",
        "changes",
        "in",
        "the",
        "retina's",
        "living",
        "cells."
      ]
    },
    {
      "text": "film: material for taking photos. cause: to make something happen. FUTURE: will cause. PRESENT: cause(s). PAST: caused.",
      "x": 0.6,
      "y": 0.75,
      "w": 0.35,
      "h": 0.22,
      "id": "r4",
      "order": 3,
      "words": [
        "film:",
        "material",
        "for",
        "taking",
        "photos.",
        "cause:",
        "to",
        "make",
        "something",
        "happen.",
        "FUTURE:",
        "will",
        "cause.",
        "PRESENT:",
        "cause(s).",
        "PAST:",
        "caused."
      ]
    }
  ]
}