{
  "page": 473,
  "image": "/books/page 473.png",
  "imageApiPath": "/api/books/page%20473.png",
  "layout": "single",
  "stats": {
    "regionCount": 7,
    "wordCount": 160,
    "imageWidth": 1242,
    "imageHeight": 1850
  },
  "panels": [
    {
      "id": "full-page",
      "label": "Full Page",
      "x": 0,
      "y": 0,
      "w": 1,
      "h": 1,
      "regionIds": [
        "r1",
        "r2",
        "r3",
        "r4",
        "r5",
        "r6",
        "r7"
      ]
    }
  ],
  "regions": [
    {
      "id": "r1",
      "order": 0,
      "text": "When the room gets too cold, the piece of metal on the outside gets shorter and moves the arm to the left. This turns on the heating system and more fuel is burned to warm the house. The purpose of putting a thermostat into a heating system is to control temperature.",
      "x": 0.1006,
      "y": 0.0389,
      "w": 0.7955,
      "h": 0.1292,
      "words": [
        "When",
        "the",
        "room",
        "gets",
        "too",
        "cold,",
        "the",
        "piece",
        "of",
        "metal",
        "on",
        "the",
        "outside",
        "gets",
        "shorter",
        "and",
        "moves",
        "the",
        "arm",
        "to",
        "the",
        "left.",
        "This",
        "turns",
        "on",
        "the",
        "heating",
        "system",
        "and",
        "more",
        "fuel",
        "is",
        "burned",
        "to",
        "warm",
        "the",
        "house.",
        "The",
        "purpose",
        "of",
        "putting",
        "a",
        "thermostat",
        "into",
        "a",
        "heating",
        "system",
        "is",
        "to",
        "control",
        "temperature."
      ],
      "conf": 96.7736,
      "source": "psm-11"
    },
    {
      "id": "r2",
      "order": 1,
      "text": "In hot climates what is important is to cool houses by",
      "x": 0.1055,
      "y": 0.4811,
      "w": 0.7971,
      "h": 0.0222,
      "words": [
        "In",
        "hot",
        "climates",
        "what",
        "is",
        "important",
        "is",
        "to",
        "cool",
        "houses",
        "by"
      ],
      "conf": 96.0299,
      "source": "psm-11"
    },
    {
      "id": "r3",
      "order": 2,
      "text": "sending fresh cold air through them. We can control the temperature of the rooms and in addition dry the air and have a climate of our own making indoors. Every ice chest has a climate of its own inside it. It is strange and surprising, but true, that ice chests are kept cold by using heat. The heat is supplied by electric power or by burn- ing gas. Scientists tell us that before long men will be using the sun’s heat to cool buildings. This will make",
      "x": 0.1039,
      "y": 0.5076,
      "w": 0.7995,
      "h": 0.2054,
      "words": [
        "sending",
        "fresh",
        "cold",
        "air",
        "through",
        "them.",
        "We",
        "can",
        "control",
        "the",
        "temperature",
        "of",
        "the",
        "rooms",
        "and",
        "in",
        "addition",
        "dry",
        "the",
        "air",
        "and",
        "have",
        "a",
        "climate",
        "of",
        "our",
        "own",
        "making",
        "indoors.",
        "Every",
        "ice",
        "chest",
        "has",
        "a",
        "climate",
        "of",
        "its",
        "own",
        "inside",
        "it.",
        "It",
        "is",
        "strange",
        "and",
        "surprising,",
        "but",
        "true,",
        "that",
        "ice",
        "chests",
        "are",
        "kept",
        "cold",
        "by",
        "using",
        "heat.",
        "The",
        "heat",
        "is",
        "supplied",
        "by",
        "electric",
        "power",
        "or",
        "by",
        "burn-",
        "ing",
        "gas.",
        "Scientists",
        "tell",
        "us",
        "that",
        "before",
        "long",
        "men",
        "will",
        "be",
        "using",
        "the",
        "sun’s",
        "heat",
        "to",
        "cool",
        "buildings.",
        "This",
        "will",
        "make"
      ],
      "conf": 95.8058,
      "source": "psm-11"
    },
    {
      "id": "r4",
      "order": 3,
      "text": "life in hot climates much easier.",
      "x": 0.1039,
      "y": 0.7178,
      "w": 0.4348,
      "h": 0.0173,
      "words": [
        "life",
        "in",
        "hot",
        "climates",
        "much",
        "easier."
      ],
      "conf": 96.5613,
      "source": "psm-11"
    },
    {
      "id": "r5",
      "order": 4,
      "text": "will dry",
      "x": 0.1055,
      "y": 0.8622,
      "w": 0.0926,
      "h": 0.0157,
      "words": [
        "will",
        "dry"
      ],
      "conf": 96.2118,
      "source": "psm-11"
    },
    {
      "id": "r6",
      "order": 5,
      "text": "dry (ies)",
      "x": 0.4477,
      "y": 0.8611,
      "w": 0.1079,
      "h": 0.0238,
      "words": [
        "dry",
        "(ies)"
      ],
      "conf": 79.2009,
      "source": "psm-11"
    },
    {
      "id": "r7",
      "order": 6,
      "text": "dried",
      "x": 0.8414,
      "y": 0.8638,
      "w": 0.0644,
      "h": 0.0124,
      "words": [
        "dried"
      ],
      "conf": 96.0156,
      "source": "psm-11"
    }
  ]
}