{
  "page": 459,
  "image": "/books/page 459.png",
  "imageApiPath": "/api/books/page%20459.png",
  "layout": "single",
  "stats": {
    "regionCount": 9,
    "wordCount": 145,
    "imageWidth": 1234,
    "imageHeight": 1850
  },
  "panels": [
    {
      "id": "full-page",
      "label": "Full Page",
      "x": 0,
      "y": 0,
      "w": 1,
      "h": 1,
      "regionIds": [
        "r1",
        "r2",
        "r3",
        "r4",
        "r5",
        "r6",
        "r7",
        "r8",
        "r9"
      ]
    }
  ],
  "regions": [
    {
      "id": "r1",
      "order": 0,
      "text": "Six thousand years ago in Egypt there were men who",
      "x": 0.0932,
      "y": 0.0357,
      "w": 0.8039,
      "h": 0.0292,
      "words": [
        "Six",
        "thousand",
        "years",
        "ago",
        "in",
        "Egypt",
        "there",
        "were",
        "men",
        "who"
      ],
      "conf": 96.6064,
      "source": "psm-11"
    },
    {
      "id": "r2",
      "order": 1,
      "text": "saw how to measure their land through their knowledge about squares and triangles.",
      "x": 0.0932,
      "y": 0.0622,
      "w": 0.8039,
      "h": 0.055,
      "words": [
        "saw",
        "how",
        "to",
        "measure",
        "their",
        "land",
        "through",
        "their",
        "knowledge",
        "about",
        "squares",
        "and",
        "triangles."
      ],
      "conf": 95.3823,
      "source": "psm-11"
    },
    {
      "id": "r3",
      "order": 2,
      "text": "How large is this square? What is its",
      "x": 0.0891,
      "y": 0.2346,
      "w": 0.2902,
      "h": 0.0698,
      "words": [
        "How",
        "large",
        "is",
        "this",
        "square?",
        "What",
        "is",
        "its"
      ],
      "conf": 88.0495,
      "source": "psm-11"
    },
    {
      "id": "r4",
      "order": 3,
      "text": "Because the square is on squared paper, it is easy to see what its size is. We count the number of small squares",
      "x": 0.0851,
      "y": 0.4508,
      "w": 0.8071,
      "h": 0.0541,
      "words": [
        "Because",
        "the",
        "square",
        "is",
        "on",
        "squared",
        "paper,",
        "it",
        "is",
        "easy",
        "to",
        "see",
        "what",
        "its",
        "size",
        "is.",
        "We",
        "count",
        "the",
        "number",
        "of",
        "small",
        "squares"
      ],
      "conf": 95.5302,
      "source": "psm-11"
    },
    {
      "id": "r5",
      "order": 4,
      "text": "in the large square. This number is the area of the square.",
      "x": 0.0851,
      "y": 0.5032,
      "w": 0.8055,
      "h": 0.0286,
      "words": [
        "in",
        "the",
        "large",
        "square.",
        "This",
        "number",
        "is",
        "the",
        "area",
        "of",
        "the",
        "square."
      ],
      "conf": 96.2859,
      "source": "psm-11"
    },
    {
      "id": "r6",
      "order": 5,
      "text": "If the small squares were an inch square, the area of the large square would be sixteen square inches. If they wero one foot square, the area of the large square would be sixteen equare feet. If they were one yard square, the area of the large square would be sixteen square yards.",
      "x": 0.081,
      "y": 0.5551,
      "w": 0.812,
      "h": 0.1314,
      "words": [
        "If",
        "the",
        "small",
        "squares",
        "were",
        "an",
        "inch",
        "square,",
        "the",
        "area",
        "of",
        "the",
        "large",
        "square",
        "would",
        "be",
        "sixteen",
        "square",
        "inches.",
        "If",
        "they",
        "wero",
        "one",
        "foot",
        "square,",
        "the",
        "area",
        "of",
        "the",
        "large",
        "square",
        "would",
        "be",
        "sixteen",
        "equare",
        "feet.",
        "If",
        "they",
        "were",
        "one",
        "yard",
        "square,",
        "the",
        "area",
        "of",
        "the",
        "large",
        "square",
        "would",
        "be",
        "sixteen",
        "square",
        "yards."
      ],
      "conf": 95.3776,
      "source": "psm-11"
    },
    {
      "id": "r7",
      "order": 6,
      "text": "Whatever the unit of measure used the relation of sido to area is thosama.",
      "x": 0.0802,
      "y": 0.6865,
      "w": 0.8104,
      "h": 0.053,
      "words": [
        "Whatever",
        "the",
        "unit",
        "of",
        "measure",
        "used",
        "the",
        "relation",
        "of",
        "sido",
        "to",
        "area",
        "is",
        "thosama."
      ],
      "conf": 95.9606,
      "source": "psm-11"
    },
    {
      "id": "r8",
      "order": 7,
      "text": "units of a measure used as one.",
      "x": 0.0827,
      "y": 0.8578,
      "w": 0.4368,
      "h": 0.0216,
      "words": [
        "units",
        "of",
        "a",
        "measure",
        "used",
        "as",
        "one."
      ],
      "conf": 94.2354,
      "source": "psm-11"
    },
    {
      "id": "r9",
      "order": 8,
      "text": "see above on this page.",
      "x": 0.154,
      "y": 0.8427,
      "w": 0.2577,
      "h": 0.0162,
      "words": [
        "see",
        "above",
        "on",
        "this",
        "page."
      ],
      "conf": 93.7118,
      "source": "psm-11"
    }
  ]
}