{
  "page": 495,
  "image": "/books/page 495.png",
  "imageApiPath": "/api/books/page%20495.png",
  "layout": "quad",
  "stats": {
    "regionCount": 4,
    "wordCount": 65,
    "imageWidth": 1234,
    "imageHeight": 1867
  },
  "panels": [
    {
      "id": "top-right",
      "label": "Top Right",
      "x": 0.5,
      "y": 0,
      "w": 0.5,
      "h": 0.5,
      "regionIds": [
        "r1",
        "r2"
      ]
    },
    {
      "id": "bottom-right",
      "label": "Bottom Right",
      "x": 0.5,
      "y": 0.5,
      "w": 0.5,
      "h": 0.5,
      "regionIds": [
        "r3",
        "r4"
      ]
    }
  ],
  "regions": [
    {
      "text": "In the distant past, only physical changes took place. This is what the science of physics studies.",
      "x": 0.1,
      "y": 0.05,
      "w": 0.85,
      "h": 0.15,
      "id": "r1",
      "order": 0,
      "words": [
        "In",
        "the",
        "distant",
        "past,",
        "only",
        "physical",
        "changes",
        "took",
        "place.",
        "This",
        "is",
        "what",
        "the",
        "science",
        "of",
        "physics",
        "studies."
      ]
    },
    {
      "text": "(Diagrams: A turning wheel and boiling water). A wheel spinning and water boiling are examples of physical changes.",
      "x": 0.1,
      "y": 0.22,
      "w": 0.85,
      "h": 0.25,
      "id": "r2",
      "order": 1,
      "words": [
        "(Diagrams:",
        "A",
        "turning",
        "wheel",
        "and",
        "boiling",
        "water).",
        "A",
        "wheel",
        "spinning",
        "and",
        "water",
        "boiling",
        "are",
        "examples",
        "of",
        "physical",
        "changes."
      ]
    },
    {
      "text": "(Diagrams: Ice forming and rain falling). Water turning to ice or falling as rain are also physical changes.",
      "x": 0.1,
      "y": 0.48,
      "w": 0.85,
      "h": 0.3,
      "id": "r3",
      "order": 2,
      "words": [
        "(Diagrams:",
        "Ice",
        "forming",
        "and",
        "rain",
        "falling).",
        "Water",
        "turning",
        "to",
        "ice",
        "or",
        "falling",
        "as",
        "rain",
        "are",
        "also",
        "physical",
        "changes."
      ]
    },
    {
      "text": "physical: having to do with material bodies and movement, rather than minds.",
      "x": 0.1,
      "y": 0.82,
      "w": 0.85,
      "h": 0.12,
      "id": "r4",
      "order": 3,
      "words": [
        "physical:",
        "having",
        "to",
        "do",
        "with",
        "material",
        "bodies",
        "and",
        "movement,",
        "rather",
        "than",
        "minds."
      ]
    }
  ]
}