{
  "page": 465,
  "image": "/books/page 465.png",
  "imageApiPath": "/api/books/page%20465.png",
  "layout": "single",
  "stats": {
    "regionCount": 8,
    "wordCount": 177,
    "imageWidth": 1242,
    "imageHeight": 1884
  },
  "panels": [
    {
      "id": "full-page",
      "label": "Full Page",
      "x": 0,
      "y": 0,
      "w": 1,
      "h": 1,
      "regionIds": [
        "r1",
        "r2",
        "r3",
        "r4",
        "r5",
        "r6",
        "r7",
        "r8"
      ]
    }
  ],
  "regions": [
    {
      "id": "r1",
      "order": 0,
      "text": "It was not until many centuries later that men put this knowledge of geometry to wide use. The development of science had to wait until the days of Galileo and Newton.",
      "x": 0.0958,
      "y": 0.0435,
      "w": 0.7979,
      "h": 0.076,
      "words": [
        "It",
        "was",
        "not",
        "until",
        "many",
        "centuries",
        "later",
        "that",
        "men",
        "put",
        "this",
        "knowledge",
        "of",
        "geometry",
        "to",
        "wide",
        "use.",
        "The",
        "development",
        "of",
        "science",
        "had",
        "to",
        "wait",
        "until",
        "the",
        "days",
        "of",
        "Galileo",
        "and",
        "Newton."
      ],
      "conf": 96.6079,
      "source": "psm-11"
    },
    {
      "id": "r2",
      "order": 1,
      "text": "In the last three centuries men’s ways of living have been and are being deeply changed by science. These changes can be compared only with three or four great earlier steps in the history of man’s development. These are the birth of language, the use of fire and farming, and the invention of writing.",
      "x": 0.0958,
      "y": 0.12,
      "w": 0.7979,
      "h": 0.1507,
      "words": [
        "In",
        "the",
        "last",
        "three",
        "centuries",
        "men’s",
        "ways",
        "of",
        "living",
        "have",
        "been",
        "and",
        "are",
        "being",
        "deeply",
        "changed",
        "by",
        "science.",
        "These",
        "changes",
        "can",
        "be",
        "compared",
        "only",
        "with",
        "three",
        "or",
        "four",
        "great",
        "earlier",
        "steps",
        "in",
        "the",
        "history",
        "of",
        "man’s",
        "development.",
        "These",
        "are",
        "the",
        "birth",
        "of",
        "language,",
        "the",
        "use",
        "of",
        "fire",
        "and",
        "farming,",
        "and",
        "the",
        "invention",
        "of",
        "writing."
      ],
      "conf": 96.0567,
      "source": "psm-11"
    },
    {
      "id": "r3",
      "order": 2,
      "text": "Here is a horse walking round and round the mouth of a well",
      "x": 0.4565,
      "y": 0.3514,
      "w": 0.4388,
      "h": 0.0435,
      "words": [
        "Here",
        "is",
        "a",
        "horse",
        "walking",
        "round",
        "and",
        "round",
        "the",
        "mouth",
        "of",
        "a",
        "well"
      ],
      "conf": 96.1208,
      "source": "psm-11"
    },
    {
      "id": "r4",
      "order": 3,
      "text": "He is pulling on a strong stick of wood which is kept turning by his motion. This moves a chain with buckets on. it. The motion of the chain carries buckets full of water up and",
      "x": 0.2601,
      "y": 0.5058,
      "w": 0.6385,
      "h": 0.0982,
      "words": [
        "He",
        "is",
        "pulling",
        "on",
        "a",
        "strong",
        "stick",
        "of",
        "wood",
        "which",
        "is",
        "kept",
        "turning",
        "by",
        "his",
        "motion.",
        "This",
        "moves",
        "a",
        "chain",
        "with",
        "buckets",
        "on.",
        "it.",
        "The",
        "motion",
        "of",
        "the",
        "chain",
        "carries",
        "buckets",
        "full",
        "of",
        "water",
        "up",
        "and"
      ],
      "conf": 96.5933,
      "source": "psm-11"
    },
    {
      "id": "r5",
      "order": 4,
      "text": "takes empty buckets down.",
      "x": 0.2601,
      "y": 0.6088,
      "w": 0.3752,
      "h": 0.0218,
      "words": [
        "takes",
        "empty",
        "buckets",
        "down."
      ],
      "conf": 96.3094,
      "source": "psm-11"
    },
    {
      "id": "r6",
      "order": 5,
      "text": "The horse has a cloth over his eyes to keep him from seeing that he is walking all the time in a circle. Would he stop if he knew he was",
      "x": 0.2568,
      "y": 0.6566,
      "w": 0.6433,
      "h": 0.0796,
      "words": [
        "The",
        "horse",
        "has",
        "a",
        "cloth",
        "over",
        "his",
        "eyes",
        "to",
        "keep",
        "him",
        "from",
        "seeing",
        "that",
        "he",
        "is",
        "walking",
        "all",
        "the",
        "time",
        "in",
        "a",
        "circle.",
        "Would",
        "he",
        "stop",
        "if",
        "he",
        "knew",
        "he",
        "was"
      ],
      "conf": 96.2614,
      "source": "psm-11"
    },
    {
      "id": "r7",
      "order": 6,
      "text": "going round in circles?",
      "x": 0.2609,
      "y": 0.7378,
      "w": 0.3148,
      "h": 0.0207,
      "words": [
        "going",
        "round",
        "in",
        "circles?"
      ],
      "conf": 96.8426,
      "source": "psm-11"
    },
    {
      "id": "r8",
      "order": 7,
      "text": "empty: with nothing inside.",
      "x": 0.1079,
      "y": 0.8477,
      "w": 0.3043,
      "h": 0.0154,
      "words": [
        "empty:",
        "with",
        "nothing",
        "inside."
      ],
      "conf": 95.3202,
      "source": "psm-11"
    }
  ]
}